adam_sim/__init__.py
adam_sim/core/topics.yaml
adam_sim/entities/__init__.py
adam_sim/entities/acceleration.py
adam_sim/entities/configuration.py
adam_sim/entities/point.py
adam_sim/entities/system.py
adam_sim/entities/vector.py
adam_sim/entities/velocity.py
adam_sim/features/__init__.py
adam_sim/features/adam/__init__.py
adam_sim/features/adam/adam.py
adam_sim/features/adam/communication/__init__.py
adam_sim/features/adam/communication/adam_repository_factory.py
adam_sim/features/adam/communication/implementations/__init__.py
adam_sim/features/adam/communication/implementations/real_adam_repository/__init__.py
adam_sim/features/adam/communication/implementations/real_adam_repository/real_adam_repository.py
adam_sim/features/adam/communication/implementations/simulated_adam_repository/__init__.py
adam_sim/features/adam/communication/implementations/simulated_adam_repository/simulated_adam_repository.py
adam_sim/features/adam/communication/implementations/simulated_adam_repository/assets/scene.xml
adam_sim/features/adam/communication/implementations/simulated_adam_repository/assets/adam/actuators.xml
adam_sim/features/adam/communication/implementations/simulated_adam_repository/assets/adam/adam.xml
adam_sim/features/adam/communication/implementations/simulated_adam_repository/assets/adam/assets.xml
adam_sim/features/adam/communication/implementations/simulated_adam_repository/assets/adam/defaults.xml
adam_sim/features/adam/communication/implementations/simulated_adam_repository/assets/adam/left_manipulator.xml
adam_sim/features/adam/communication/implementations/simulated_adam_repository/assets/adam/right_manipulator.xml
adam_sim/features/adam/communication/implementations/simulated_adam_repository/assets/meshes/base.stl
adam_sim/features/adam/communication/implementations/simulated_adam_repository/assets/meshes/body.stl
adam_sim/features/adam/communication/implementations/simulated_adam_repository/assets/meshes/body1.stl
adam_sim-1.0.2.dist-info/LICENSE
adam_sim-1.0.2.dist-info/METADATA
adam_sim-1.0.2.dist-info/WHEEL
adam_sim-1.0.2.dist-info/top_level.txt
adam_sim-1.0.2.dist-info/RECORD
