Metadata-Version: 2.1
Name: adam-sim
Version: 1.0.2
Summary: A simulator of ADAM (Autonomous Domestic Ambidextrous Manipulator), a mobile robot manipulator consisting of a base with two Degrees of Freedom (DoF) and two Universal Robots UR3 of 6 DoF each.
Author: Vistor
Project-URL: Homepage, https://github.com/vistormu/adam_simulator
Project-URL: Bug Tracker, https://github.com/vistormu/adam_simulator/issues
Classifier: Programming Language :: Python :: 3
Classifier: License :: OSI Approved :: MIT License
Classifier: Operating System :: OS Independent
Requires-Python: >=3.10
License-File: LICENSE
Requires-Dist: numpy
Requires-Dist: mujoco
Requires-Dist: mujoco-python-viewer
Requires-Dist: pyyaml
Requires-Dist: pandas
Requires-Dist: matplotlib
Requires-Dist: paho-mqtt
Requires-Dist: vclog
